bow_api/__init__.py
bow_api/bow_api.py
bow_api-4.3.0.2831.data/data/requirements.txt
bow_data/__init__.py
bow_data/bow_client_pb2.py
bow_data/bow_client_pb2.pyi
bow_data/bow_client_sdk_pb2.py
bow_data/bow_client_sdk_pb2.pyi
bow_data/bow_codec.py
bow_data/bow_common_pb2.py
bow_data/bow_common_pb2.pyi
bow_data/bow_companion_pb2.py
bow_data/bow_companion_pb2.pyi
bow_data/bow_data_audio_pb2.py
bow_data/bow_data_audio_pb2.pyi
bow_data/bow_data_common_pb2.py
bow_data/bow_data_common_pb2.pyi
bow_data/bow_data_exteroception_pb2.py
bow_data/bow_data_exteroception_pb2.pyi
bow_data/bow_data_interoception_pb2.py
bow_data/bow_data_interoception_pb2.pyi
bow_data/bow_data_motor_pb2.py
bow_data/bow_data_motor_pb2.pyi
bow_data/bow_data_octree_pb2.py
bow_data/bow_data_octree_pb2.pyi
bow_data/bow_data_pb2.py
bow_data/bow_data_pb2.pyi
bow_data/bow_data_tactile_pb2.py
bow_data/bow_data_tactile_pb2.pyi
bow_data/bow_data_vision_pb2.py
bow_data/bow_data_vision_pb2.pyi
bow_data/bow_messages_pb2.py
bow_data/bow_messages_pb2.pyi
bow_data/bow_robot_pb2.py
bow_data/bow_robot_pb2.pyi
bow_data/bow_robot_sdk_pb2.py
bow_data/bow_robot_sdk_pb2.pyi
bow_data/bow_structs_pb2.py
bow_data/bow_structs_pb2.pyi
lib_client/.gitignore
lib_client/LICENSE
lib_client/__init__.py
lib_client/_animus_client.pyd
lib_client/animus_client.h
lib_client/animus_client.py
lib_client/animus_client_wrap.c
lib_client/libanimus_client.dll
lib_client/libanimus_client.lib
lib_client/libgcc_s_seh-1.dll
lib_client/libstdc++-6.dll
lib_client/libwinpthread-1.dll
bow_api-4.3.0.2831.dist-info/LICENSE
bow_api-4.3.0.2831.dist-info/METADATA
bow_api-4.3.0.2831.dist-info/WHEEL
bow_api-4.3.0.2831.dist-info/top_level.txt
bow_api-4.3.0.2831.dist-info/RECORD
