Metadata-Version: 2.1
Name: bow_api
Version: 4.3.0.2831
Summary: BOW SDK for Python 3 developed by Bettering Our Worlds (BOW) Ltd.
Home-page: https://www.usebow.com
Author: Daniel Camilleri
Author-email: support@bow.ltd
License: Proprietary. (C) Bettering Our Worlds (BOW) Ltd.
Classifier: Programming Language :: Python
Classifier: Programming Language :: Python :: 3
Classifier: License :: Other/Proprietary License
Classifier: Topic :: Software Development :: Libraries
Classifier: Intended Audience :: Developers
Requires-Python: >=3.7
License-File: LICENSE
Requires-Dist: numpy
Requires-Dist: scikit-build
Requires-Dist: opencv-python
Requires-Dist: wheel
Requires-Dist: protobuf~=4.21
Requires-Dist: typing
Requires-Dist: typing-extensions
